[
  {
    "ContainingType": "Serilog_JWT_Other.Controllers.AuthorController",
    "Method": "CreateAuthor",
    "RelativePath": "api/Author/CreateAuthor",
    "HttpMethod": "POST",
    "IsController": true,
    "Order": 0,
    "Parameters": [
      {
        "Name": "model",
        "Type": "Serilog_JWT_Other.Models.Author.CreateAuthorRequestModel",
        "IsRequired": true
      }
    ],
    "ReturnTypes": []
  },
  {
    "ContainingType": "Serilog_JWT_Other.Controllers.AuthorController",
    "Method": "DeleteAuthorById",
    "RelativePath": "api/Author/DeleteAuthorById",
    "HttpMethod": "POST",
    "IsController": true,
    "Order": 0,
    "Parameters": [
      {
        "Name": "model",
        "Type": "Serilog_JWT_Other.Models.Author.DeleteAuthorByIdRequestModel",
        "IsRequired": true
      }
    ],
    "ReturnTypes": []
  },
  {
    "ContainingType": "Serilog_JWT_Other.Controllers.AuthorController",
    "Method": "GetAuthorByIdHttpGet",
    "RelativePath": "api/Author/GetAuthorById",
    "HttpMethod": "GET",
    "IsController": true,
    "Order": 0,
    "Parameters": [
      {
        "Name": "id",
        "Type": "System.String",
        "IsRequired": false
      }
    ],
    "ReturnTypes": []
  },
  {
    "ContainingType": "Serilog_JWT_Other.Controllers.AuthorController",
    "Method": "GetAuthorById",
    "RelativePath": "api/Author/GetAuthorById",
    "HttpMethod": "POST",
    "IsController": true,
    "Order": 0,
    "Parameters": [
      {
        "Name": "model",
        "Type": "Serilog_JWT_Other.Models.Author.GetAuthorByIdRequestModel",
        "IsRequired": true
      }
    ],
    "ReturnTypes": []
  },
  {
    "ContainingType": "Serilog_JWT_Other.Controllers.AuthorController",
    "Method": "GetAuthorList",
    "RelativePath": "api/Author/GetAuthorList",
    "HttpMethod": "POST",
    "IsController": true,
    "Order": 0,
    "Parameters": [
      {
        "Name": "model",
        "Type": "Serilog_JWT_Other.Models.Author.GetAuthorListRequestModel",
        "IsRequired": true
      }
    ],
    "ReturnTypes": []
  },
  {
    "ContainingType": "Serilog_JWT_Other.Controllers.AuthorController",
    "Method": "UpdateAuthorById",
    "RelativePath": "api/Author/UpdateAuthorById",
    "HttpMethod": "POST",
    "IsController": true,
    "Order": 0,
    "Parameters": [
      {
        "Name": "model",
        "Type": "Serilog_JWT_Other.Models.Author.UpdateAuthorByIdRequestModel",
        "IsRequired": true
      }
    ],
    "ReturnTypes": []
  },
  {
    "ContainingType": "Serilog_JWT_Other.Controllers.WeatherForecastController",
    "Method": "Get",
    "RelativePath": "WeatherForecast",
    "HttpMethod": "GET",
    "IsController": true,
    "Order": 0,
    "Parameters": [],
    "ReturnTypes": [
      {
        "Type": "System.Collections.Generic.IEnumerable\u00601[[Serilog_JWT_Other.WeatherForecast, Serilog_JWT_Other, Version=1.0.0.0, Culture=neutral, PublicKeyToken=null]]",
        "MediaTypes": [
          "text/plain",
          "application/json",
          "text/json"
        ],
        "StatusCode": 200
      }
    ],
    "EndpointName": "GetWeatherForecast"
  },
  {
    "ContainingType": "Serilog_JWT_Other.Controllers.WeatherForecastController",
    "Method": "LogTest",
    "RelativePath": "WeatherForecast/LoggingTest",
    "HttpMethod": "GET",
    "IsController": true,
    "Order": 0,
    "Parameters": [],
    "ReturnTypes": [
      {
        "Type": "System.Void",
        "MediaTypes": [],
        "StatusCode": 200
      }
    ]
  }
]